[
  {
    "nazwa": "Owocal Bio Charsznickie Ogórki Kiszone",
    "sklad": "ogórki, woda, sól, koper, czosnek, ziele angielskie, liść laurowy",
    "wartosci_odzywcze": {
      "E_kcal": "11",
      "B": "1,69",
      "T": "b.d.",
      "N": "b.d.",
      "W": "1,4",
      "C": "b.d.",
      "Bl": "b.d.",
      "S": "0,5"
    },
    "zrodlo": "tyl-proc/IMG_9865.png"
  },
  {
    "nazwa": "Dole Tropical Gold Pineapple Chunks",
    "sklad": "ananas, sok ananasowy",
    "wartosci_odzywcze": {
      "E_kcal": "58",
      "B": "0",
      "T": "0",
      "N": "0",
      "W": "13",
      "C": "12",
      "Bl": "b.d.",
      "S": "0"
    },
    "zrodlo": "tyl-proc/IMG_9768.png"
  },
  {
    "nazwa": "Dole Tropical Gold Pineapple Slices",
    "sklad": "ananas, sok ananasowy",
    "wartosci_odzywcze": {
      "E_kcal": "58",
      "B": "0",
      "T": "0",
      "N": "0",
      "W": "13",
      "C": "12",
      "Bl": "b.d.",
      "S": "0"
    },
    "zrodlo": "tyl-proc/IMG_9769.png"
  },
  {
    "nazwa": "Mutti Sos Do Makaronu z Papryką Chili",
    "sklad": "pulpa pomidorowa 60%, passata (przecier) z pomidorów Pizzutello 20%, koncentrat pomidorowy 7,5%, papryka czerwona, oliwa z oliwek, cebula, pietruszka, papryka chili 0,5%, bazylia, sól, naturalne aromaty, czosnek, skórka papryki",
    "wartosci_odzywcze": {
      "E_kcal": "52",
      "B": "1,6",
      "T": "2,7",
      "N": "0,4",
      "W": "4,6",
      "C": "4,2",
      "Bl": "b.d.",
      "S": "0,94"
    },
    "zrodlo": "tyl-proc/IMG_9756.png"
  },
  {
    "nazwa": "Mutti Sos Do Makaronu z Bazylią",
    "sklad": "pulpa pomidorowa 60%, passata (przecier) z pomidorów Rossoro 23%, koncentrat pomidorowy 10,2%, oliwa z oliwek, cebula, bazylia 1,5%, marchew, naturalne aromaty, sól",
    "wartosci_odzywcze": {
      "E_kcal": "56",
      "B": "1,6",
      "T": "2,8",
      "N": "0,5",
      "W": "5,3",
      "C": "4,5",
      "Bl": "b.d.",
      "S": "0,81"
    },
    "zrodlo": "tyl-proc/IMG_9758.png"
  },
  {
    "nazwa": "Mutti Sos Do Makaronu z Serem Parmigiano Reggiano",
    "sklad": "pulpa pomidorowa 60,6%, passata (przecier) z pomidorów Rossoro 20%, koncentrat pomidorowy 7,1%, ser Parmigiano Reggiano ChNP (mleko, sól, podpuszczka) 4%, oliwa z oliwek, cebula szalotka, sól, naturalne aromaty, pieprz czarny",
    "wartosci_odzywcze": {
      "E_kcal": "67",
      "B": "3,1",
      "T": "3,5",
      "N": "1,0",
      "W": "5,0",
      "C": "b.d.",
      "Bl": "b.d.",
      "S": "0,88"
    },
    "zrodlo": "tyl-proc/IMG_9760.png"
  },
  {
    "nazwa": "Mutti Sos Do Makaronu Bolognese",
    "sklad": "pulpa pomidorowa 40%, przecier z pomidorów daktylowych 20%, woda 10%, koncentrat pomidorowy 7%, cebula 7%, marchew 5%, oliwa z oliwek, grillowany bakłażan 2,5%, grillowana cukinia 2,5%, czosnek 1,8%, sól, bazylia 0,5%, czarny pieprz, oregano",
    "wartosci_odzywcze": {
      "E_kcal": "57",
      "B": "1,5",
      "T": "3,0",
      "N": "b.d.",
      "W": "5,6",
      "C": "4,5",
      "Bl": "b.d.",
      "S": "0,79"
    },
    "zrodlo": "tyl-proc/IMG_9762.png"
  },
  {
    "nazwa": "Combino Sos Pomidorowy Arrabbiata",
    "sklad": "krojone pomidory 80%, koncentrat pomidorów, oliwa z oliwek, cebula, rafinowany olej z oliwek, sól, ziele piegowego, papryka czerwona, czosnek, 0,5% naturalny aromat, papryka pietruszkowa, cukier, 0,15% papryczka chili",
    "wartosci_odzywcze": {
      "E_kcal": "b.d.",
      "B": "b.d.",
      "T": "b.d.",
      "N": "b.d.",
      "W": "b.d.",
      "C": "b.d.",
      "Bl": "b.d.",
      "S": "b.d."
    },
    "zrodlo": "tyl-proc/IMG_9933.png"
  },
  {
    "nazwa": "Combino Sos Pomidorowy Basilico",
    "sklad": "krojone pomidory 79%, woda, oliwa z oliwek 2%, koncentrat pomidorowy, cukier, sól, skrobia modyfikowana kukurydziana, bazylia, naturalny aromat",
    "wartosci_odzywcze": {
      "E_kcal": "b.d.",
      "B": "b.d.",
      "T": "b.d.",
      "N": "b.d.",
      "W": "b.d.",
      "C": "b.d.",
      "Bl": "b.d.",
      "S": "b.d."
    },
    "zrodlo": "tyl-proc/IMG_9936.png"
  }
]
